super_inlines/__init__.py
super_inlines/admin.py
super_inlines/grappelli_integration/__init__.py
super_inlines/grappelli_integration/static/admin/js/inlines.js
super_inlines/grappelli_integration/static/admin/js/inlines.min.js
super_inlines/grappelli_integration/static/grappelli/js/grappelli.min.js
super_inlines/grappelli_integration/static/grappelli/js/jquery.grp_inline.js
super_inlines/grappelli_integration/templates/admin/edit_inline/stacked.html
super_inlines/grappelli_integration/templates/admin/edit_inline/tabular.html
super_inlines/static/admin/js/inlines.js
super_inlines/static/admin/js/inlines.min.js
super_inlines/templates/admin/edit_inline/stacked.html
super_inlines/templates/admin/edit_inline/tabular.html
super_inlines/templatetags/__init__.py
super_inlines/templatetags/super_inlines.py
django_super_inlines-0.2.2.dist-info/LICENSE
django_super_inlines-0.2.2.dist-info/METADATA
django_super_inlines-0.2.2.dist-info/WHEEL
django_super_inlines-0.2.2.dist-info/top_level.txt
django_super_inlines-0.2.2.dist-info/RECORD
