Metadata-Version: 2.1
Name: django-super-inlines
Version: 0.2.2
Summary: Adds useful features to inlines, such as the ability to nest them.
Home-page: https://github.com/BertrandBordage/django-super-inlines
Author: Bertrand Bordage
Author-email: bordage.bertrand@gmail.com
License: BSD
Classifier: Development Status :: 3 - Alpha
Classifier: Framework :: Django
Classifier: Intended Audience :: Developers
Classifier: License :: OSI Approved :: BSD License
Classifier: Operating System :: OS Independent
Classifier: Programming Language :: Python :: 2
Classifier: Programming Language :: Python :: 2.7
Classifier: Programming Language :: Python :: 3
Classifier: Programming Language :: Python :: 3.2
Classifier: Programming Language :: Python :: 3.3
Classifier: Programming Language :: Python :: 3.4
Classifier: Topic :: Internet :: WWW/HTTP
License-File: LICENSE
Requires-Dist: Django >=2.2
